{
  "pets": [
    {
      "id" : 0,
      "especie": "Cachorro",
      "nome": "Calabreso",
      "sexo": "M",
      "idade": "1 anos e 4 meses",
      "peso": "2.5",
      "tutor": "Juliano chagas"
    },
    {
      "id" : 1,
      "especie": "Cachorro",
      "nome": "Calabreso",
      "sexo": "M",
      "idade": "1 anos e 4 meses",
      "peso": "2.5",
      "tutor": "Juliano chagas"
    },
    {
      "id" : 2,
      "especie": "Cachorro",
      "nome": "Calabreso",
      "sexo": "M",
      "idade": "1 anos e 4 meses",
      "peso": "2.5",
      "tutor": "Juliano chagas"
    },
    {
      "id" : 3,
      "especie": "Cachorro",
      "nome": "Calabreso",
      "sexo": "M",
      "idade": "1 anos e 4 meses",
      "peso": "2.5",
      "tutor": "Juliano chagas"
    },
    {
      "id" : 4,
      "especie": "Cachorro",
      "nome": "Calabreso",
      "sexo": "M",
      "idade": "1 anos e 4 meses",
      "peso": "2.5",
      "tutor": "Juliano chagas"
    },
    {
      "id" : 5,
      "especie": "Cachorro",
      "nome": "Calabreso",
      "sexo": "M",
      "idade": "1 anos e 4 meses",
      "peso": "2.5",
      "tutor": "Juliano chagas"
    }
  ]
}